cronosapi/__init__.py
cronosapi/account.py
cronosapi/api.py
cronosapi/contract.py
cronosapi-0.1.2.dist-info/LICENSE.txt
cronosapi-0.1.2.dist-info/METADATA
cronosapi-0.1.2.dist-info/WHEEL
cronosapi-0.1.2.dist-info/top_level.txt
cronosapi-0.1.2.dist-info/RECORD
