Metadata-Version: 2.1
Name: cronosapi
Version: 0.1.2
Summary: Python Wrapper for Cronos API
Home-page: https://github.com/JulienCoutault/cronos-api
Author: Julien Coutault
Author-email: cronos-api@juliencoutault.fr
License: MIT
Keywords: Cronos,API,CRO,Crypto.com,Blockchain
Classifier: Development Status :: 1 - Planning
Classifier: Intended Audience :: Developers
Classifier: Topic :: Software Development :: Build Tools
Classifier: License :: OSI Approved :: MIT License
Classifier: Programming Language :: Python :: 3
License-File: LICENSE.txt
Requires-Dist: requests
